orcaset/__init__.py
orcaset/decorators.py
orcaset/node.py
orcaset/py.typed
orcaset/utils.py
orcaset/financial/__init__.py
orcaset/financial/accrual.py
orcaset/financial/accrual_node.py
orcaset/financial/balance_node.py
orcaset/financial/payment_node.py
orcaset/financial/period.py
orcaset/financial/yearfrac.py
orcaset-0.1.2.dist-info/METADATA
orcaset-0.1.2.dist-info/WHEEL
orcaset-0.1.2.dist-info/licenses/LICENSE
orcaset-0.1.2.dist-info/RECORD
