Metadata-Version: 2.4
Name: orcaset
Version: 0.1.2
Summary: Open financial modeling toolkit
Project-URL: homepage, https://github.com/Orcaset/orcaset
License-Expression: SSPL-1.0
License-File: LICENSE
Requires-Python: >=3.12
Requires-Dist: mypy>=1.17.0
Requires-Dist: python-dateutil>=2.8.2
